log_helper/__init__.py
log_helper/log_helper.py
log_helper/models/__init__.py
log_helper/models/log_model.py
log_helper_bit3-1.2.1.dist-info/METADATA
log_helper_bit3-1.2.1.dist-info/WHEEL
log_helper_bit3-1.2.1.dist-info/top_level.txt
log_helper_bit3-1.2.1.dist-info/RECORD
