Metadata-Version: 2.1
Name: log-helper-bit3
Version: 1.2.1
Summary: Es un paquete que brinda la posibilidad a las clases de almacenar los pasos que se siguen en esta.
Home-page: https://github.com/bitcubico/LogHelperPy
Author: Mauricio Montoya Medrano
Author-email: mcubico33@gmail.com
License: UNKNOWN
Keywords: python,log,helper,mcubico,bitcubico technology
Platform: UNKNOWN
Classifier: Development Status :: 4 - Beta
Classifier: Programming Language :: Python :: 3.8
Classifier: License :: OSI Approved :: MIT License
Classifier: Operating System :: MacOS :: MacOS X
Classifier: Operating System :: Microsoft :: Windows
Classifier: Operating System :: Unix
Requires-Python: >=3.8
